algorithms_daemon/WorkerBroker_pb2.py
algorithms_daemon/WorkerBroker_pb2_grpc.py
algorithms_daemon/__init__.py
algorithms_daemon/auth.py
algorithms_daemon/config.py
algorithms_daemon/daemon.py
algorithms_daemon/redis_cache.py
algorithms_daemon/run.py
algorithms_daemon/slide_source.py
algorithms_daemon-0.2.0.dist-info/LICENSE
algorithms_daemon-0.2.0.dist-info/METADATA
algorithms_daemon-0.2.0.dist-info/WHEEL
algorithms_daemon-0.2.0.dist-info/top_level.txt
algorithms_daemon-0.2.0.dist-info/RECORD
